almabtrieb/__init__.py
almabtrieb/__main__.py
almabtrieb/base.py
almabtrieb/cli_methods.py
almabtrieb/exceptions.py
almabtrieb/model.py
almabtrieb/py.typed
almabtrieb/stream.py
almabtrieb/test_base.py
almabtrieb/test_init.py
almabtrieb/test_real.py
almabtrieb/test_stream.py
almabtrieb/test_trigger.py
almabtrieb/util.py
almabtrieb/version.py
almabtrieb/amqp/__init__.py
almabtrieb/amqp/message_type.py
almabtrieb/amqp/test_amqp.py
almabtrieb/amqp/test_message_type.py
almabtrieb/mqtt/__init__.py
almabtrieb/mqtt/base.py
almabtrieb/mqtt/message_type.py
almabtrieb/mqtt/test_base.py
almabtrieb/mqtt/test_mqtt.py
almabtrieb-0.2.9.dist-info/METADATA
almabtrieb-0.2.9.dist-info/WHEEL
almabtrieb-0.2.9.dist-info/entry_points.txt
almabtrieb-0.2.9.dist-info/RECORD
