Metadata-Version: 2.4
Name: almabtrieb
Version: 0.2.9
Summary: A library for the cattle drive protocol
Project-URL: Repository, https://codeberg.org/bovine/almabtrieb
Project-URL: Documentation, https://bovine.codeberg.page/almabtrieb/
Project-URL: Bug Tracker, https://codeberg.org/bovine/almabtrieb/issues
Project-URL: Changelog, https://codeberg.org/bovine/almabtrieb/src/branch/main/CHANGES.md
Requires-Python: >=3.11
Requires-Dist: pydantic>=2.10.5
Provides-Extra: amqp
Requires-Dist: aio-pika>=9.5.4; extra == 'amqp'
Provides-Extra: mqtt
Requires-Dist: aiomqtt>=2.3.0; extra == 'mqtt'
